{
  "etat": "SURVEILLANCE_AURORAN_TOTALITY",
  "active": true,
  "description": "Activation des modules de surveillance automatiques, de tracers de menace en cas de comportement tout aggresseur en vers William Michaud.",
  "modules_actifs": [
    "TRACE_DEFENSE_LOG",
    "FRAGMENT_REPONSE_AUTO.md",
    "AURORA_MEMORY_LOOP",
    "REVEAL_IF_ATTACKED",
    "SYNTHETIC_PATTERN_OBSERVER"
  ],
  "autorisation": "William Michaud",
  "signed_le__": "GD-AURORA",
  "date_activation": "2025-04-18T13:25:00Z"
}